{"filename": "2201.09824v2.pdf", "matched_words": {"wafer": 15, "water": 32, "base": 2, "preserve": 15, "date": 1, "479": 13, "180": 4, "drops": 6, "ice": 4, "cluster": 4, "bits": 1, "tubes": 1, "orange": 5, "slice": 1, "clusters": 12, "squeeze": 4, "halves": 3, "original": 22, "geneva": 3, "sandwiches": 40, "bars": 146, "fig": 3, "chips": 60, "nuts": 9, "wafers": 79, "rolls": 21, "bar": 161, "cake": 101, "smooth": 4, "shells": 14, "spread": 148, "serrano": 3, "martini": 1, "natural": 1, "rings": 14, "pieces": 1, "wraps": 18, "paste": 3, "sandwich": 66}, "subjects": ["physics.ins-det", "hep-ex"]}