{"filename": "1909.01421v1.pdf", "matched_words": {"mix": 9, "snack": 1, "slice": 1, "drink": 138, "lasagna": 109, "prunes": 25, "clusters": 12, "food": 1, "dip": 78, "simplicity": 4, "dressing": 308, "spaghetti": 247, "fig": 3, "cubes": 4, "trees": 2, "date": 1, "base": 2, "cluster": 4, "onion": 8, "bar": 161, "natural": 1, "roll": 5, "water": 32, "sliders": 5, "pieces": 1, "smooth": 4, "spread": 148, "drops": 6, "meal": 1, "bars": 146, "beer": 6, "martini": 1, "kettle": 5, "original": 22, "gouda": 8, "mini": 5, "cheese": 221, "treat": 3, "dates": 20, "disco": 6, "orange": 5, "hash": 4, "heart": 2, "tenders": 1, "milk": 325, "bits": 1, "eggs": 34, "180": 4, "bacon": 254, "cod": 17, "grapefruit": 16, "banana": 8, "whiskey": 1}, "subjects": ["cs.AI", "cs.DB"]}