{"filename": "2211.05100v4.pdf", "matched_words": {"natural": 1, "salmon": 30, "kale": 46, "lemon": 4, "bar": 161, "original": 22, "carolina": 1, "orange": 5, "spam": 1, "dressing": 308, "fries": 1, "waffle": 11, "jos": 1, "halves": 3, "seltzer": 151, "dal": 1, "kernels": 2, "squares": 3, "flan": 9, "slice": 1, "smooth": 4, "ham": 212, "brussels": 3, "clusters": 12, "dates": 20, "trees": 2, "bordeaux": 3, "danish": 73, "lemons": 19, "mix": 9, "roux": 11, "kaiser": 3, "fragile": 3, "alfredo": 1, "cluster": 4, "base": 2, "camembert": 11}, "subjects": ["cs.CL"]}