{"filename": "1707.00952v3.pdf", "matched_words": {"cluster": 4, "spread": 148, "natural": 1, "zur": 3, "bars": 146, "smooth": 4, "treats": 5, "180": 4, "simplicity": 4, "pasta": 39, "pieces": 1, "shells": 14, "instant": 3, "treat": 3, "spreads": 4, "date": 1, "squares": 3, "mix": 9, "parfait": 18, "drops": 6, "chaos": 3, "preserve": 15, "calabrese": 1, "bar": 161, "almond": 3, "479": 13, "egg": 21, "pop": 9, "heart": 2, "orange": 5, "original": 22, "croissant": 12, "slices": 2, "graham": 1, "slice": 1, "dates": 20, "rings": 14}, "subjects": ["gr-qc"]}