{"filename": "2502.11324v1.pdf", "matched_words": {"blossoms": 1, "soybeans": 10, "crisp": 1, "prunes": 25, "sugar": 17, "barbecue": 6, "potatoes": 39, "original": 22, "trees": 2, "squares": 3, "cluster": 4, "grapes": 5, "sweet": 17, "lavender": 6, "180": 4, "chunks": 8, "egg": 21, "blueberries": 422, "food": 1, "barley": 12, "pumpkins": 6, "lemonade": 497, "apple": 12, "chia": 21, "natural": 1, "rye": 3, "nectar": 104, "strawberries": 94, "classic": 1, "kale": 46, "water": 32, "radishes": 6, "oats": 12, "cherry": 11, "clusters": 12, "bars": 146, "base": 2, "sandwiches": 40, "corn": 48, "preserves": 176, "vegetables": 6}, "subjects": ["stat.ML", "cs.LG"]}