{"filename": "2309.08928v1.pdf", "matched_words": {"fig": 3, "potatoes": 39, "bar": 161, "beer": 6, "sticks": 9, "lemon": 4, "vodka": 1, "eggs": 34, "macaroni": 9, "hamburger": 19, "cheese": 221, "peppers": 11, "strawberry": 49, "pizza": 264, "vegetables": 6, "drink": 138, "spices": 5, "cluster": 4, "carrots": 138, "puree": 7, "paste": 3, "brandy": 1, "tomato": 11, "bacon": 254, "natural": 1, "broth": 60, "chicken": 42, "beef": 44, "mexican": 1, "base": 2, "parmesan": 1, "ice": 4, "milk": 325, "butter": 130, "cod": 17, "meat": 13, "water": 32, "breadcrumbs": 4, "dip": 78, "cookies": 602, "sugar": 17, "mustard": 175, "vegetable": 3, "juice": 188, "jalapenos": 7, "meals": 3, "sweet": 17, "stock": 6, "sauce": 326, "onion": 8, "smooth": 4, "cider": 14, "chews": 10, "food": 1, "jos": 1, "saffron": 1, "pieces": 1, "cream": 3, "rice": 36, "preserves": 176, "original": 22, "meal": 1, "tomatoes": 19, "salad": 56, "sprinkle": 4, "eggplant": 6, "cinnamon": 20, "scallops": 15, "artichokes": 11}, "subjects": ["cs.CV"]}