{"filename": "2503.17201v1.pdf", "matched_words": {"dairy": 6, "thyme": 16, "sugar": 17, "spread": 148, "original": 22, "cluster": 4, "onion": 8, "almonds": 374, "oil": 1, "mozzarella": 14, "egg": 21, "eggs": 34, "steak": 5, "meal": 1, "sauce": 326, "allspice": 7, "salt": 117, "food": 1, "spices": 5, "date": 1, "beef": 44, "vinegar": 82, "chicken": 42, "figs": 8, "fig": 3, "meat": 13, "tomato": 11, "natural": 1, "bread": 188, "nuts": 9, "bear": 1, "preserve": 15, "pepper": 11, "water": 32, "cheese": 221, "cinnamon": 20, "clusters": 12, "vegetables": 6}, "subjects": ["cs.IR"]}