{"filename": "2406.11833v2.pdf", "matched_words": {"sauce": 326, "bars": 146, "doughnuts": 4, "water": 32, "rabbit": 1, "danish": 73, "treat": 3, "bar": 161, "clusters": 12, "date": 1, "nectar": 104, "bear": 1, "blossoms": 1, "original": 22, "cider": 14, "mystery": 3, "butterflies": 4, "croissant": 12, "orange": 5, "preserve": 15, "tomato": 11, "smooth": 4, "lavender": 6, "pasta": 39, "meat": 13, "natural": 1, "spaghetti": 247, "oil": 1, "chicken": 42, "fig": 3, "milk": 325, "blend": 3, "cluster": 4, "food": 1}, "subjects": ["cs.CV", "cs.AI", "cs.LG"]}