{"filename": "2407.04648v1.pdf", "matched_words": {"bits": 1, "180": 4, "apple": 12, "cod": 17, "pop": 9, "fig": 3, "plain": 1, "natural": 1, "serrano": 3, "pieces": 1, "base": 2, "orange": 5, "prunes": 25, "spread": 148, "instant": 3, "shells": 14, "sauce": 326, "treat": 3, "mix": 9, "date": 1, "ham": 212, "cluster": 4, "bar": 161, "hash": 4, "trees": 2, "clusters": 12, "kernels": 2, "shortening": 8, "organic": 1, "original": 22, "cherry": 11, "preserve": 15, "smooth": 4, "simplicity": 4, "mole": 11}, "subjects": ["cond-mat.mtrl-sci", "cs.AI", "cs.DB", "physics.data-an"]}