{"filename": "2407.12823v1.pdf", "matched_words": {"squares": 3, "pieces": 1, "fig": 3, "chai": 29, "sandwich": 66, "stock": 6, "meal": 1, "cakes": 4, "base": 2, "natural": 1, "date": 1, "drops": 6, "drink": 138, "food": 1, "kaiser": 3, "plain": 1, "tea": 83, "ice": 4, "bar": 161, "grapes": 5, "bars": 146, "tomatoes": 19, "plums": 1, "original": 22, "sandwiches": 40, "cream": 3, "ham": 212, "egg": 21, "pop": 9, "water": 32, "nector": 3, "coffee": 31, "simplicity": 4, "eggs": 34, "meals": 3, "cocoa": 7}, "subjects": ["cs.CL", "cs.AI"]}