{"filename": "2110.12088v2.pdf", "matched_words": {"cluster": 4, "squirrel": 1, "food": 1, "trout": 1, "plain": 1, "mushroom": 5, "base": 2, "apple": 12, "mini": 5, "rabbit": 1, "beaver": 1, "pears": 5, "sweet": 17, "turtle": 1, "orange": 5, "mix": 9, "crab": 2, "bowls": 1, "bear": 1, "raccoon": 1, "clusters": 12, "trees": 2, "oranges": 4, "vegetables": 6, "natural": 1, "peppers": 11, "original": 22, "butterfly": 4, "lobster": 1, "apples": 71, "bar": 161, "mushrooms": 43}, "subjects": ["cs.LG", "stat.ML"]}