{"filename": "2208.11637v1.pdf", "matched_words": {"natural": 1, "chocolat": 6, "mini": 5, "original": 22, "treat": 3, "cubes": 4, "pears": 5, "orange": 5, "ice": 4, "180": 4, "bananas": 1, "instant": 3, "slice": 1, "smooth": 4, "simplicity": 4, "dates": 20, "tubes": 1, "date": 1, "fig": 3, "spread": 148, "mix": 9, "preserve": 15, "kaiser": 3, "burgers": 10, "sage": 5, "punch": 33, "shells": 14, "base": 2, "lard": 39, "chocolates": 65, "slices": 2}, "subjects": ["astro-ph.SR", "physics.plasm-ph", "physics.space-ph"]}