{"filename": "2011.09232v1.pdf", "matched_words": {"banana": 8, "peanut": 25, "lemon": 4, "crab": 2, "beer": 6, "garlic": 66, "cherry": 11, "pizza": 264, "baguette": 26, "cluster": 4, "grape": 7, "chaos": 3, "onion": 8, "pineapple": 39, "pepper": 11, "bow": 6, "coconut": 12, "moose": 1, "stock": 6, "ostrich": 1, "clusters": 12, "479": 13, "butterfly": 4, "goat": 1, "roll": 5, "lobster": 1, "salt": 117, "grinder": 21, "almond": 3, "rice": 36, "kaiser": 3, "raisin": 4, "180": 4, "honey": 304, "cake": 101, "kiwi": 10, "bread": 188, "apricot": 15, "chicken": 42, "rabbit": 1, "papaya": 6, "jam": 178}, "subjects": ["q-bio.NC"]}