{"filename": "0705.1730v1.pdf", "matched_words": {"browning": 9, "cakes": 4, "smooth": 4, "spirals": 9, "plain": 1, "blossoms": 1, "bow": 6, "date": 1, "base": 2, "original": 22, "sausage": 72, "lentils": 241, "sweet": 17, "180": 4, "danish": 73, "dal": 1, "drops": 6, "bar": 161, "natural": 1, "stock": 6, "scones": 22, "turtle": 1, "mediterranean": 6, "egg": 21, "coppa": 10, "assorted": 3, "classic": 1, "scone": 5, "noodle": 3, "cream": 3, "rabbit": 1, "dates": 20, "meatballs": 71, "rye": 3, "ice": 4, "millet": 1, "banana": 8, "bordeaux": 3, "mix": 9, "roll": 5, "whiting": 4, "chicken": 42, "frosting": 23, "meals": 3, "rings": 14, "chill": 1, "bark": 7, "chips": 60, "curry": 12, "pops": 79, "lemonade": 497, "crab": 2, "speck": 1, "chunks": 8, "corn": 48, "sage": 5, "bacon": 254, "shells": 14, "bars": 146, "beaver": 1, "clusters": 12, "bear": 1, "beans": 9, "royale": 1, "nuts": 9, "479": 13, "wings": 1, "singles": 16, "soup": 95, "preserve": 15, "octopus": 5, "barley": 12, "heart": 2, "carolina": 1, "spread": 148, "bits": 1, "dips": 6, "rolls": 21, "sauce": 326, "jam": 178, "pieces": 1, "pancakes": 49, "oats": 12, "salt": 117, "fudge": 13, "turtles": 4, "bueno": 4, "peas": 55, "slices": 2, "drink": 138, "water": 32, "yam": 5, "cluster": 4, "raccoon": 1, "kaiser": 3, "pop": 9, "cake": 101}, "subjects": ["astro-ph"]}