{"filename": "1306.6905v2.pdf", "matched_words": {"tubes": 1, "genova": 1, "orange": 5, "rolls": 21, "original": 22, "manhattan": 1, "figs": 8, "punch": 33, "clusters": 12, "bologna": 154, "180": 4, "buffalo": 5, "squares": 3, "drops": 6, "geneva": 3, "natural": 1, "cluster": 4, "rice": 36, "roll": 5, "slices": 2, "bars": 146, "mexican": 1, "collard": 5, "splash": 2, "fig": 3, "dates": 20, "rings": 14, "turkey": 31, "water": 32, "chips": 60, "date": 1, "bits": 1, "spread": 148}, "subjects": ["physics.ins-det", "hep-ex"]}