{"filename": "1608.07551v1.pdf", "matched_words": {"spread": 148, "mix": 9, "wraps": 18, "bars": 146, "classic": 1, "treat": 3, "orange": 5, "bits": 1, "base": 2, "figs": 8, "alfredo": 1, "peanut": 25, "chaos": 3, "180": 4, "squeeze": 4, "roll": 5, "bear": 1, "slices": 2, "fudge": 13, "fig": 3, "natural": 1, "date": 1, "cluster": 4, "drops": 6, "nori": 3, "preserve": 15, "smooth": 4, "treats": 5, "simplicity": 4, "apples": 71, "dal": 1, "preserves": 176, "squeezers": 1, "chips": 60, "colby": 8, "rice": 36, "pie": 114, "wafer": 15, "clusters": 12, "graham": 1, "butter": 130, "rings": 14, "heart": 2, "wafers": 79, "original": 22, "slice": 1, "brownies": 94}, "subjects": ["quant-ph", "nlin.PS", "physics.optics"]}