{"filename": "2301.03947v1.pdf", "matched_words": {"kiwi": 10, "clusters": 12, "classic": 1, "eggplants": 2, "cherry": 11, "fig": 3, "strawberries": 94, "cluster": 4, "food": 1, "pears": 5, "pepper": 11, "vegetable": 3, "orange": 5, "kiwifruit": 1, "water": 32, "lamb": 2, "sweet": 17, "preserve": 15, "cucumbers": 9, "tomatoes": 19, "apple": 12, "original": 22, "strawberry": 49, "simplicity": 4, "natural": 1, "preserves": 176, "base": 2, "oranges": 4, "tomato": 11, "peppers": 11, "pieces": 1, "drops": 6}, "subjects": ["cs.RO", "cs.AI", "cs.CV"]}