{"filename": "2411.08243v3.pdf", "matched_words": {"original": 22, "cluster": 4, "pie": 114, "soup": 95, "food": 1, "lard": 39, "jos": 1, "rice": 36, "fragile": 3, "base": 2, "mexican": 1, "ginger": 21, "fries": 1, "sweet": 17, "basil": 31, "nori": 3, "saffron": 1, "fig": 3, "bar": 161, "cherry": 11, "bacon": 254, "strudel": 15, "geneva": 3, "natural": 1, "graham": 1, "kale": 46, "clusters": 12, "ice": 4, "oregano": 15, "noodles": 7, "ale": 4, "dal": 1, "treat": 3, "date": 1, "chia": 21, "ham": 212}, "subjects": ["cs.CL", "cs.CY"]}