{"filename": "2411.18664v1.pdf", "matched_words": {"blossoms": 1, "tropical": 14, "squirrel": 1, "orange": 5, "beer": 6, "original": 22, "trees": 2, "wings": 1, "yam": 5, "lavender": 6, "spaghetti": 247, "sparkling": 8, "meal": 1, "food": 1, "donut": 5, "beef": 44, "chicken": 42, "fig": 3, "rabbit": 1, "apple": 12, "natural": 1, "bear": 1, "classic": 1, "smooth": 4, "jelly": 154, "cakes": 4, "splash": 2, "rice": 36, "preserve": 15, "water": 32, "stroganoff": 5, "drink": 138, "preserves": 176}, "subjects": ["cs.CV"]}