{"filename": "2411.14688v1.pdf", "matched_words": {"pepperoni": 226, "juice": 188, "yeast": 1, "roll": 5, "cider": 14, "original": 22, "treat": 3, "slices": 2, "flour": 17, "tomatoes": 19, "oil": 1, "basil": 31, "drinks": 5, "mozzarella": 14, "egg": 21, "eggs": 34, "sauce": 326, "salt": 117, "spices": 5, "muffin": 52, "pizza": 264, "cubes": 4, "fig": 3, "lemon": 4, "tomato": 11, "mixer": 4, "muffins": 149, "bar": 161, "mix": 9, "water": 32, "cheese": 221, "tubes": 1, "base": 2, "drink": 138, "soda": 1315, "ice": 4, "ham": 212}, "subjects": ["cs.CV", "cs.CL", "cs.LG"]}