{"filename": "2204.03100v1.pdf", "matched_words": {"turkey": 31, "natural": 1, "bear": 1, "mint": 13, "tenders": 1, "pie": 114, "original": 22, "treat": 3, "oaxaca": 216, "carolina": 1, "ice": 4, "water": 32, "180": 4, "spam": 1, "fries": 1, "manhattan": 1, "mexican": 1, "pita": 2, "smooth": 4, "clusters": 12, "food": 1, "dates": 20, "date": 1, "trees": 2, "coppa": 10, "pieces": 1, "spread": 148, "mix": 9, "preserve": 15, "meals": 3, "cluster": 4, "brains": 1, "base": 2, "oil": 1, "caribbean": 6, "spreads": 4}, "subjects": ["cs.CY", "cs.HC", "cs.LG"]}